cyberfusion/SecurityTXTPolicyServer/__init__.py
cyberfusion/SecurityTXTPolicyServer/database.py
cyberfusion/SecurityTXTPolicyServer/endpoints.py
cyberfusion/SecurityTXTPolicyServer/middleware.py
cyberfusion/SecurityTXTPolicyServer/server.py
cyberfusion/SecurityTXTPolicyServer/settings.py
cyberfusion/SecurityTXTPolicyServer/utilities.py
cyberfusion/SecurityTXTPolicyServer/exceptions/__init__.py
cyberfusion/SecurityTXTPolicyServer/exceptions/database.py
cyberfusion/SecurityTXTPolicyServer/exceptions/http_host_header.py
security_txt_policy_server-1.0.4.dist-info/METADATA
security_txt_policy_server-1.0.4.dist-info/WHEEL
security_txt_policy_server-1.0.4.dist-info/entry_points.txt
security_txt_policy_server-1.0.4.dist-info/top_level.txt
security_txt_policy_server-1.0.4.dist-info/RECORD
