Metadata-Version: 2.1
Name: security-txt-policy-server
Version: 1.0.4
Summary: security-txt-policy-server serves `.well-known/security.txt` files.
Author-email: Cyberfusion <support@cyberfusion.io>
Project-URL: Source, https://github.com/CyberfusionIO/security-txt-policy-server
Requires-Dist: starlette ==0.38.2
Requires-Dist: uvicorn ==0.30.6
Requires-Dist: validators ==0.33.0
